README.md
setup.py
easybq/__init__.py
easybq/client.py
easybq/schema.py
easybq.egg-info/PKG-INFO
easybq.egg-info/SOURCES.txt
easybq.egg-info/dependency_links.txt
easybq.egg-info/requires.txt
easybq.egg-info/top_level.txt