Metadata-Version: 1.2
Name: easybq
Version: 0.1.2
Summary: BigQuery Wrapper
Home-page: https://github.com/ukwksk/easybq
Author: ukwksk
Author-email: pylibs@ukwksk.co
Maintainer: ukwksk
Maintainer-email: pylibs@ukwksk.co
License: MIT
Keywords: Google BigQuery
Platform: UNKNOWN
Classifier: Programming Language :: Python :: 3.6
Classifier: License :: OSI Approved :: MIT License
Requires-Python: >=3.6
